<Maps next_id="2">
    <Map id="1" cols="10" rows="5">
        <Tile col="0" row="0">
            <Sprite row="0" col="0">grass-border</Sprite>
            <Solid>0</Solid>
            <Start>0</Start>
            <Finish>0</Finish>
        </Tile>
        <Tile col="1" row="0">
            <Sprite row="0" col="0">blank</Sprite>
            <Solid>0</Solid>
            <Start>0</Start>
            <Finish>0</Finish>
        </Tile>
        <Tile col="2" row="0">
            <Sprite row="0" col="0">blank</Sprite>
            <Solid>0</Solid>
            <Start>0</Start>
            <Finish>0</Finish>
        </Tile>
        <Tile col="3" row="0">
            <Sprite row="0" col="0">grass</Sprite>
            <Solid>0</Solid>
            <Start>0</Start>
            <Finish>0</Finish>
        </Tile>
        <Tile col="4" row="0">
            <Sprite row="0" col="1">chests</Sprite>
            <Solid>0</Solid>
            <Start>0</Start>
            <Finish>0</Finish>
        </Tile>
        <Tile col="5" row="0">
            <Sprite row="0" col="0">grass</Sprite>
            <Solid>0</Solid>
            <Start>0</Start>
            <Finish>0</Finish>
        </Tile>
        <Tile col="6" row="0">
            <Sprite row="0" col="0">blank</Sprite>
            <Solid>0</Solid>
            <Start>0</Start>
            <Finish>0</Finish>
        </Tile>
        <Tile col="7" row="0">
            <Sprite row="0" col="0">blank</Sprite>
            <Solid>0</Solid>
            <Start>0</Start>
            <Finish>0</Finish>
        </Tile>
        <Tile col="8" row="0">
            <Sprite row="0" col="0">blank</Sprite>
            <Solid>0</Solid>
            <Start>0</Start>
            <Finish>0</Finish>
        </Tile>
        <Tile col="9" row="0">
            <Sprite row="0" col="0">blank</Sprite>
            <Solid>0</Solid>
            <Start>0</Start>
            <Finish>0</Finish>
        </Tile>
        <Tile col="0" row="1">
            <Sprite row="0" col="0">blank</Sprite>
            <Solid>0</Solid>
            <Start>0</Start>
            <Finish>0</Finish>
        </Tile>
        <Tile col="1" row="1">
            <Sprite row="0" col="0">blank</Sprite>
            <Solid>0</Solid>
            <Start>0</Start>
            <Finish>0</Finish>
        </Tile>
        <Tile col="2" row="1">
            <Sprite row="0" col="1">chests</Sprite>
            <Solid>0</Solid>
            <Start>0</Start>
            <Finish>0</Finish>
        </Tile>
        <Tile col="3" row="1">
            <Sprite row="0" col="0">grass</Sprite>
            <Solid>0</Solid>
            <Start>0</Start>
            <Finish>0</Finish>
        </Tile>
        <Tile col="4" row="1">
            <Sprite row="0" col="0">grass</Sprite>
            <Solid>0</Solid>
            <Start>0</Start>
            <Finish>0</Finish>
        </Tile>
        <Tile col="5" row="1">
            <Sprite row="0" col="0">grass</Sprite>
            <Solid>0</Solid>
            <Start>0</Start>
            <Finish>0</Finish>
        </Tile>
        <Tile col="6" row="1">
            <Sprite row="0" col="1">chests</Sprite>
            <Solid>0</Solid>
            <Start>0</Start>
            <Finish>0</Finish>
        </Tile>
        <Tile col="7" row="1">
            <Sprite row="0" col="0">blank</Sprite>
            <Solid>0</Solid>
            <Start>0</Start>
            <Finish>0</Finish>
        </Tile>
        <Tile col="8" row="1">
            <Sprite row="0" col="0">blank</Sprite>
            <Solid>0</Solid>
            <Start>0</Start>
            <Finish>0</Finish>
        </Tile>
        <Tile col="9" row="1">
            <Sprite row="0" col="0">blank</Sprite>
            <Solid>0</Solid>
            <Start>0</Start>
            <Finish>0</Finish>
        </Tile>
        <Tile col="0" row="2">
            <Sprite row="0" col="0">blank</Sprite>
            <Solid>0</Solid>
            <Start>1</Start>
            <Finish>0</Finish>
        </Tile>
        <Tile col="1" row="2">
            <Sprite row="0" col="0">blank</Sprite>
            <Solid>0</Solid>
            <Start>0</Start>
            <Finish>0</Finish>
        </Tile>
        <Tile col="2" row="2">
            <Sprite row="0" col="0">blank</Sprite>
            <Solid>0</Solid>
            <Start>0</Start>
            <Finish>0</Finish>
        </Tile>
        <Tile col="3" row="2">
            <Sprite row="0" col="0">blank</Sprite>
            <Solid>0</Solid>
            <Start>0</Start>
            <Finish>0</Finish>
        </Tile>
        <Tile col="4" row="2">
            <Sprite row="0" col="0">blank</Sprite>
            <Solid>0</Solid>
            <Start>0</Start>
            <Finish>0</Finish>
        </Tile>
        <Tile col="5" row="2">
            <Sprite row="0" col="0">blank</Sprite>
            <Solid>0</Solid>
            <Start>0</Start>
            <Finish>0</Finish>
        </Tile>
        <Tile col="6" row="2">
            <Sprite row="0" col="0">blank</Sprite>
            <Solid>0</Solid>
            <Start>0</Start>
            <Finish>0</Finish>
        </Tile>
        <Tile col="7" row="2">
            <Sprite row="0" col="0">blank</Sprite>
            <Solid>0</Solid>
            <Start>0</Start>
            <Finish>0</Finish>
        </Tile>
        <Tile col="8" row="2">
            <Sprite row="0" col="0">blank</Sprite>
            <Solid>0</Solid>
            <Start>0</Start>
            <Finish>0</Finish>
        </Tile>
        <Tile col="9" row="2">
            <Sprite row="0" col="0">blank</Sprite>
            <Solid>0</Solid>
            <Start>0</Start>
            <Finish>1</Finish>
        </Tile>
        <Tile col="0" row="3">
            <Sprite row="0" col="0">blank</Sprite>
            <Solid>0</Solid>
            <Start>0</Start>
            <Finish>0</Finish>
        </Tile>
        <Tile col="1" row="3">
            <Sprite row="0" col="0">grass-border</Sprite>
            <Solid>0</Solid>
            <Start>0</Start>
            <Finish>0</Finish>
        </Tile>
        <Tile col="2" row="3">
            <Sprite row="0" col="0">blank</Sprite>
            <Solid>0</Solid>
            <Start>0</Start>
            <Finish>0</Finish>
        </Tile>
        <Tile col="3" row="3">
            <Sprite row="0" col="0">blank</Sprite>
            <Solid>0</Solid>
            <Start>0</Start>
            <Finish>0</Finish>
        </Tile>
        <Tile col="4" row="3">
            <Sprite row="0" col="0">blank</Sprite>
            <Solid>0</Solid>
            <Start>0</Start>
            <Finish>0</Finish>
        </Tile>
        <Tile col="5" row="3">
            <Sprite row="0" col="0">blank</Sprite>
            <Solid>0</Solid>
            <Start>0</Start>
            <Finish>0</Finish>
        </Tile>
        <Tile col="6" row="3">
            <Sprite row="0" col="0">blank</Sprite>
            <Solid>0</Solid>
            <Start>0</Start>
            <Finish>0</Finish>
        </Tile>
        <Tile col="7" row="3">
            <Sprite row="0" col="0">blank</Sprite>
            <Solid>0</Solid>
            <Start>0</Start>
            <Finish>0</Finish>
        </Tile>
        <Tile col="8" row="3">
            <Sprite row="0" col="0">blank</Sprite>
            <Solid>0</Solid>
            <Start>0</Start>
            <Finish>0</Finish>
        </Tile>
        <Tile col="9" row="3">
            <Sprite row="0" col="0">blank</Sprite>
            <Solid>0</Solid>
            <Start>0</Start>
            <Finish>0</Finish>
        </Tile>
        <Tile col="0" row="4">
            <Sprite row="0" col="0">grass</Sprite>
            <Solid>0</Solid>
            <Start>0</Start>
            <Finish>0</Finish>
        </Tile>
        <Tile col="1" row="4">
            <Sprite row="0" col="0">blank</Sprite>
            <Solid>0</Solid>
            <Start>0</Start>
            <Finish>0</Finish>
        </Tile>
        <Tile col="2" row="4">
            <Sprite row="0" col="0">blank</Sprite>
            <Solid>0</Solid>
            <Start>0</Start>
            <Finish>0</Finish>
        </Tile>
        <Tile col="3" row="4">
            <Sprite row="0" col="0">blank</Sprite>
            <Solid>0</Solid>
            <Start>0</Start>
            <Finish>0</Finish>
        </Tile>
        <Tile col="4" row="4">
            <Sprite row="0" col="0">blank</Sprite>
            <Solid>0</Solid>
            <Start>0</Start>
            <Finish>0</Finish>
        </Tile>
        <Tile col="5" row="4">
            <Sprite row="0" col="0">blank</Sprite>
            <Solid>0</Solid>
            <Start>0</Start>
            <Finish>0</Finish>
        </Tile>
        <Tile col="6" row="4">
            <Sprite row="0" col="0">blank</Sprite>
            <Solid>0</Solid>
            <Start>0</Start>
            <Finish>0</Finish>
        </Tile>
        <Tile col="7" row="4">
            <Sprite row="0" col="0">blank</Sprite>
            <Solid>0</Solid>
            <Start>0</Start>
            <Finish>0</Finish>
        </Tile>
        <Tile col="8" row="4">
            <Sprite row="0" col="0">blank</Sprite>
            <Solid>0</Solid>
            <Start>0</Start>
            <Finish>0</Finish>
        </Tile>
        <Tile col="9" row="4">
            <Sprite row="0" col="0">blank</Sprite>
            <Solid>0</Solid>
            <Start>0</Start>
            <Finish>0</Finish>
        </Tile>
    </Map>
</Maps>
